commons_io/__init__.py
commons_io/file_utils.py
commons_io-0.1.4.dist-info/METADATA
commons_io-0.1.4.dist-info/WHEEL
commons_io-0.1.4.dist-info/RECORD
